ddeutil/io/__about__.py
ddeutil/io/__init__.py
ddeutil/io/__regex.py
ddeutil/io/__type.py
ddeutil/io/config.py
ddeutil/io/dirs.py
ddeutil/io/exceptions.py
ddeutil/io/files.py
ddeutil/io/paths.py
ddeutil/io/register.py
ddeutil/io/stores.py
ddeutil/io/utils.py
ddeutil_io-0.2.17.dist-info/licenses/LICENSE
ddeutil_io-0.2.17.dist-info/METADATA
ddeutil_io-0.2.17.dist-info/WHEEL
ddeutil_io-0.2.17.dist-info/top_level.txt
ddeutil_io-0.2.17.dist-info/RECORD
