Metadata-Version: 2.4
Name: ddeutil-io
Version: 0.2.17
Summary: Input/Output transport objects
Author-email: ddeutils <korawich.anu@gmail.com>
License: MIT
Project-URL: Homepage, https://github.com/korawica/ddeutil-io/
Project-URL: Source Code, https://github.com/korawica/ddeutil-io/
Keywords: io,utility
Classifier: Topic :: Utilities
Classifier: Natural Language :: English
Classifier: Development Status :: 4 - Beta
Classifier: Intended Audience :: Developers
Classifier: Operating System :: OS Independent
Classifier: Programming Language :: Python
Classifier: Programming Language :: Python :: 3 :: Only
Classifier: Programming Language :: Python :: 3.9
Classifier: Programming Language :: Python :: 3.10
Classifier: Programming Language :: Python :: 3.11
Classifier: Programming Language :: Python :: 3.12
Classifier: Programming Language :: Python :: 3.13
Requires-Python: >=3.9.13
License-File: LICENSE
Requires-Dist: ddeutil>=0.4.7
Requires-Dist: tzdata>=2025.2
Provides-Extra: test
Requires-Dist: ddeutil-io[all]; extra == "test"
Requires-Dist: typing-extensions; extra == "test"
Provides-Extra: all
Requires-Dist: msgpack>=1.1.0; extra == "all"
Requires-Dist: pyyaml>=6.0.2; extra == "all"
Requires-Dist: rtoml>=0.12.0; extra == "all"
Requires-Dist: fmtutil==1.0.15; extra == "all"
Requires-Dist: deepdiff>=8.5.0; extra == "all"
Requires-Dist: python-dateutil>=2.9.0.post0; extra == "all"
Requires-Dist: types-python-dateutil>=2.9.0.20250516; extra == "all"
Provides-Extra: register
Requires-Dist: fmtutil==1.0.15; extra == "register"
Requires-Dist: deepdiff>=8.5.0; extra == "register"
Requires-Dist: python-dateutil>=2.9.0.post0; extra == "register"
Requires-Dist: types-python-dateutil>=2.9.0.20250516; extra == "register"
Provides-Extra: yaml
Requires-Dist: pyyaml>=6.0.2; extra == "yaml"
Provides-Extra: toml
Requires-Dist: rtoml>=0.12.0; extra == "toml"
Provides-Extra: msgpack
Requires-Dist: msgpack>=1.1.0; extra == "msgpack"
Dynamic: license-file
